{
    "analysis": {
        "avg_acc_test_teacher": 88.9064888888889,
        "avg_acc_test_student": 87.81400000000001,
        "avg_acc_test_distilled": 88.62986666666669,
        "std_acc_test_teacher": 0.3861589951536515,
        "std_acc_test_student": 1.393400980383906,
        "std_acc_test_distilled": 0.38350141831955153,
        "avg_acc_train_teacher": 99.3736444444444,
        "avg_acc_train_student": 98.3636,
        "avg_acc_train_distilled": 99.34013333333333,
        "std_acc_train_teacher": 1.8336692159460257,
        "std_acc_train_student": 1.8366305299027312,
        "std_acc_train_distilled": 1.1071252660843123,
        "final_acc_test_distilled": 88.86800000000001,
        "final_acc_test_teacher": 89.12400000000001,
        "final_acc_test_student": 85.312,
        "final_acc_train_distilled": 99.928,
        "final_acc_train_teacher": 99.996,
        "final_acc_train_student": 96.844,
        "sum_time_train_teacher": 2585.8703906536102,
        "sum_time_train_student": 1558.6761147975922,
        "sum_time_train_distilled": 1617.3346710205078,
        "sum_time_test_teacher": 1544.65611410141,
        "sum_time_test_student": 895.416065454483,
        "sum_time_test_distilled": 1013.481390953064,
        "avg_time_train_teacher": 28.73189322948456,
        "avg_time_train_student": 17.318623497751023,
        "avg_time_train_distilled": 9.09865692059199,
        "avg_time_test_teacher": 17.16284571223789,
        "avg_time_test_student": 9.9490673939387,
        "avg_time_test_distilled": 9.109130648771922,
        "total_time": 10694.623916387558
    },
    "params": {
        "teacher": {
            "C": 8000,
            "T": 6000,
            "s": 7.0,
            "epochs": 30
        },
        "student": {
            "C": 4000,
            "T": 6000,
            "s": 7.0,
            "epochs": 60
        },
        "temperature": 3.0,
        "alpha": 0.5,
        "weighted_clauses": true,
        "number_of_state_bits": 8,
        "combined_epochs": 90
    },
    "experiment_name": "IMDB",
    "timestamp": "2025-03-03 20:48:22",
    "id": "IMDB_tC8000_sC4000_tT6000_sT6000_ts7.0_ss7.0_te30_se60_temp3.0_a0.5",
    "results": {
        "acc_test_teacher": {
            "0": 86.80799999999999,
            "1": 87.852,
            "2": 87.884,
            "3": 87.44800000000001,
            "4": 88.032,
            "5": 87.972,
            "6": 88.776,
            "7": 88.144,
            "8": 88.664,
            "9": 88.876,
            "10": 88.632,
            "11": 88.728,
            "12": 88.94,
            "13": 88.94,
            "14": 89.004,
            "15": 89.032,
            "16": 88.888,
            "17": 89.128,
            "18": 89.144,
            "19": 89.196,
            "20": 89.228,
            "21": 89.08,
            "22": 89.144,
            "23": 89.244,
            "24": 89.2,
            "25": 88.912,
            "26": 88.996,
            "27": 89.108,
            "28": 89.044,
            "29": 89.076,
            "30": 88.876,
            "31": 89.05199999999999,
            "32": 88.956,
            "33": 88.78399999999999,
            "34": 89.064,
            "35": 89.108,
            "36": 89.104,
            "37": 88.992,
            "38": 88.956,
            "39": 89.14800000000001,
            "40": 89.19200000000001,
            "41": 89.1,
            "42": 88.96,
            "43": 89.132,
            "44": 89.20400000000001,
            "45": 89.064,
            "46": 89.196,
            "47": 89.14800000000001,
            "48": 89.116,
            "49": 89.20400000000001,
            "50": 89.068,
            "51": 89.036,
            "52": 89.12,
            "53": 89.044,
            "54": 88.9,
            "55": 88.992,
            "56": 88.888,
            "57": 88.92,
            "58": 88.884,
            "59": 88.996,
            "60": 89.108,
            "61": 89.16,
            "62": 88.976,
            "63": 89.084,
            "64": 89.004,
            "65": 88.992,
            "66": 88.936,
            "67": 88.828,
            "68": 88.82,
            "69": 88.94800000000001,
            "70": 89.01599999999999,
            "71": 88.94800000000001,
            "72": 88.992,
            "73": 88.98,
            "74": 88.844,
            "75": 88.676,
            "76": 88.888,
            "77": 88.90400000000001,
            "78": 88.90400000000001,
            "79": 88.908,
            "80": 88.736,
            "81": 88.992,
            "82": 88.98,
            "83": 89.128,
            "84": 89.12,
            "85": 89.1,
            "86": 88.928,
            "87": 89.044,
            "88": 89.19200000000001,
            "89": 89.12400000000001
        },
        "acc_test_student": {
            "0": 86.856,
            "1": 87.756,
            "2": 88.02799999999999,
            "3": 87.932,
            "4": 88.14800000000001,
            "5": 88.69200000000001,
            "6": 88.592,
            "7": 87.768,
            "8": 88.832,
            "9": 88.804,
            "10": 89.116,
            "11": 88.348,
            "12": 88.752,
            "13": 87.82799999999999,
            "14": 88.78399999999999,
            "15": 88.98,
            "16": 88.684,
            "17": 88.92,
            "18": 88.896,
            "19": 89.024,
            "20": 87.728,
            "21": 88.472,
            "22": 88.396,
            "23": 88.79599999999999,
            "24": 88.376,
            "25": 88.57199999999999,
            "26": 88.464,
            "27": 86.276,
            "28": 86.488,
            "29": 86.256,
            "30": 87.728,
            "31": 88.292,
            "32": 88.55199999999999,
            "33": 88.28399999999999,
            "34": 89.108,
            "35": 88.048,
            "36": 88.828,
            "37": 88.96,
            "38": 88.188,
            "39": 86.35199999999999,
            "40": 87.464,
            "41": 88.464,
            "42": 88.96,
            "43": 88.488,
            "44": 88.676,
            "45": 88.244,
            "46": 88.764,
            "47": 88.64800000000001,
            "48": 88.94,
            "49": 89.084,
            "50": 88.916,
            "51": 88.77199999999999,
            "52": 88.90400000000001,
            "53": 88.89200000000001,
            "54": 88.604,
            "55": 89.012,
            "56": 88.744,
            "57": 89.144,
            "58": 88.89200000000001,
            "59": 88.924,
            "60": 88.952,
            "61": 88.864,
            "62": 88.40400000000001,
            "63": 88.996,
            "64": 88.832,
            "65": 88.2,
            "66": 87.968,
            "67": 87.912,
            "68": 85.656,
            "69": 88.324,
            "70": 87.792,
            "71": 88.128,
            "72": 87.94800000000001,
            "73": 86.812,
            "74": 84.396,
            "75": 87.168,
            "76": 86.06,
            "77": 86.328,
            "78": 84.98,
            "79": 85.2,
            "80": 86.028,
            "81": 84.244,
            "82": 85.732,
            "83": 86.696,
            "84": 84.872,
            "85": 87.41600000000001,
            "86": 82.884,
            "87": 84.492,
            "88": 85.224,
            "89": 85.312
        },
        "acc_test_distilled": {
            "0": 86.80799999999999,
            "1": 87.852,
            "2": 87.884,
            "3": 87.44800000000001,
            "4": 88.032,
            "5": 87.972,
            "6": 88.776,
            "7": 88.144,
            "8": 88.664,
            "9": 88.876,
            "10": 88.632,
            "11": 88.728,
            "12": 88.94,
            "13": 88.94,
            "14": 89.004,
            "15": 89.032,
            "16": 88.888,
            "17": 89.128,
            "18": 89.144,
            "19": 89.196,
            "20": 89.228,
            "21": 89.08,
            "22": 89.144,
            "23": 89.244,
            "24": 89.2,
            "25": 88.912,
            "26": 88.996,
            "27": 89.108,
            "28": 89.044,
            "29": 89.076,
            "30": 86.36,
            "31": 87.848,
            "32": 88.004,
            "33": 88.228,
            "34": 88.22,
            "35": 88.452,
            "36": 88.56,
            "37": 88.432,
            "38": 88.504,
            "39": 88.508,
            "40": 88.436,
            "41": 88.656,
            "42": 88.05199999999999,
            "43": 88.5,
            "44": 88.77199999999999,
            "45": 88.28,
            "46": 88.69200000000001,
            "47": 88.616,
            "48": 88.75999999999999,
            "49": 88.588,
            "50": 88.8,
            "51": 88.708,
            "52": 88.696,
            "53": 88.548,
            "54": 88.82,
            "55": 88.684,
            "56": 88.7,
            "57": 88.444,
            "58": 88.768,
            "59": 88.824,
            "60": 88.744,
            "61": 88.724,
            "62": 88.81599999999999,
            "63": 88.84,
            "64": 88.78399999999999,
            "65": 88.788,
            "66": 88.664,
            "67": 88.828,
            "68": 88.68,
            "69": 88.876,
            "70": 88.52799999999999,
            "71": 88.876,
            "72": 88.804,
            "73": 89.0,
            "74": 88.77199999999999,
            "75": 88.9,
            "76": 88.86,
            "77": 88.956,
            "78": 88.996,
            "79": 88.828,
            "80": 88.89200000000001,
            "81": 88.70400000000001,
            "82": 88.7,
            "83": 88.844,
            "84": 88.936,
            "85": 88.88000000000001,
            "86": 88.828,
            "87": 88.56,
            "88": 88.856,
            "89": 88.86800000000001
        },
        "acc_train_teacher": {
            "0": 89.69200000000001,
            "1": 92.184,
            "2": 93.068,
            "3": 93.352,
            "4": 94.844,
            "5": 95.06,
            "6": 97.552,
            "7": 96.94800000000001,
            "8": 98.4,
            "9": 98.54,
            "10": 98.69200000000001,
            "11": 99.012,
            "12": 99.236,
            "13": 99.60799999999999,
            "14": 99.53999999999999,
            "15": 99.69200000000001,
            "16": 99.66000000000001,
            "17": 99.74,
            "18": 99.88,
            "19": 99.884,
            "20": 99.9,
            "21": 99.928,
            "22": 99.94800000000001,
            "23": 99.964,
            "24": 99.968,
            "25": 99.968,
            "26": 99.976,
            "27": 99.996,
            "28": 100.0,
            "29": 100.0,
            "30": 100.0,
            "31": 100.0,
            "32": 99.992,
            "33": 99.988,
            "34": 99.996,
            "35": 100.0,
            "36": 99.996,
            "37": 99.988,
            "38": 99.996,
            "39": 99.996,
            "40": 100.0,
            "41": 100.0,
            "42": 100.0,
            "43": 100.0,
            "44": 100.0,
            "45": 100.0,
            "46": 100.0,
            "47": 100.0,
            "48": 100.0,
            "49": 100.0,
            "50": 100.0,
            "51": 100.0,
            "52": 100.0,
            "53": 100.0,
            "54": 99.988,
            "55": 100.0,
            "56": 99.996,
            "57": 99.988,
            "58": 99.984,
            "59": 99.976,
            "60": 99.976,
            "61": 99.98,
            "62": 99.97200000000001,
            "63": 99.976,
            "64": 99.976,
            "65": 99.97200000000001,
            "66": 99.97200000000001,
            "67": 99.96000000000001,
            "68": 99.968,
            "69": 99.976,
            "70": 99.976,
            "71": 99.97200000000001,
            "72": 99.976,
            "73": 99.984,
            "74": 99.968,
            "75": 99.984,
            "76": 100.0,
            "77": 99.996,
            "78": 99.992,
            "79": 99.988,
            "80": 99.98,
            "81": 100.0,
            "82": 99.996,
            "83": 99.992,
            "84": 100.0,
            "85": 99.996,
            "86": 99.996,
            "87": 99.992,
            "88": 100.0,
            "89": 99.996
        },
        "acc_train_student": {
            "0": 89.376,
            "1": 91.73599999999999,
            "2": 93.03200000000001,
            "3": 94.268,
            "4": 95.044,
            "5": 96.14399999999999,
            "6": 96.256,
            "7": 95.724,
            "8": 97.468,
            "9": 97.676,
            "10": 98.344,
            "11": 97.60799999999999,
            "12": 98.488,
            "13": 97.408,
            "14": 98.432,
            "15": 98.784,
            "16": 98.02,
            "17": 98.744,
            "18": 99.076,
            "19": 98.892,
            "20": 97.088,
            "21": 97.94,
            "22": 97.964,
            "23": 98.904,
            "24": 97.832,
            "25": 98.792,
            "26": 98.86399999999999,
            "27": 96.97200000000001,
            "28": 97.712,
            "29": 97.34,
            "30": 98.644,
            "31": 99.292,
            "32": 99.156,
            "33": 99.016,
            "34": 99.47200000000001,
            "35": 98.908,
            "36": 99.624,
            "37": 99.69200000000001,
            "38": 99.36,
            "39": 98.164,
            "40": 98.872,
            "41": 99.36,
            "42": 99.684,
            "43": 99.708,
            "44": 99.66000000000001,
            "45": 99.488,
            "46": 99.616,
            "47": 99.488,
            "48": 99.624,
            "49": 99.70400000000001,
            "50": 99.8,
            "51": 99.816,
            "52": 99.776,
            "53": 99.764,
            "54": 99.74,
            "55": 99.736,
            "56": 99.756,
            "57": 99.66000000000001,
            "58": 99.74,
            "59": 99.76,
            "60": 99.78399999999999,
            "61": 99.836,
            "62": 99.78,
            "63": 99.772,
            "64": 99.844,
            "65": 99.744,
            "66": 99.712,
            "67": 99.76,
            "68": 98.38799999999999,
            "69": 99.656,
            "70": 99.592,
            "71": 99.732,
            "72": 99.79599999999999,
            "73": 99.324,
            "74": 97.068,
            "75": 99.372,
            "76": 98.568,
            "77": 98.964,
            "78": 98.176,
            "79": 97.636,
            "80": 98.47200000000001,
            "81": 96.596,
            "82": 97.892,
            "83": 99.19200000000001,
            "84": 97.272,
            "85": 99.28,
            "86": 95.38,
            "87": 96.20400000000001,
            "88": 97.08,
            "89": 96.844
        },
        "acc_train_distilled": {
            "0": 89.69200000000001,
            "1": 92.184,
            "2": 93.068,
            "3": 93.352,
            "4": 94.844,
            "5": 95.06,
            "6": 97.552,
            "7": 96.94800000000001,
            "8": 98.4,
            "9": 98.54,
            "10": 98.69200000000001,
            "11": 99.012,
            "12": 99.236,
            "13": 99.60799999999999,
            "14": 99.53999999999999,
            "15": 99.69200000000001,
            "16": 99.66000000000001,
            "17": 99.74,
            "18": 99.88,
            "19": 99.884,
            "20": 99.9,
            "21": 99.928,
            "22": 99.94800000000001,
            "23": 99.964,
            "24": 99.968,
            "25": 99.968,
            "26": 99.976,
            "27": 99.996,
            "28": 100.0,
            "29": 100.0,
            "30": 93.28,
            "31": 95.612,
            "32": 96.852,
            "33": 97.824,
            "34": 98.05199999999999,
            "35": 98.088,
            "36": 98.72800000000001,
            "37": 98.804,
            "38": 98.912,
            "39": 99.084,
            "40": 99.036,
            "41": 99.072,
            "42": 98.956,
            "43": 99.24,
            "44": 99.496,
            "45": 99.4,
            "46": 99.488,
            "47": 99.6,
            "48": 99.656,
            "49": 99.548,
            "50": 99.68,
            "51": 99.66000000000001,
            "52": 99.7,
            "53": 99.612,
            "54": 99.792,
            "55": 99.616,
            "56": 99.72,
            "57": 99.616,
            "58": 99.764,
            "59": 99.756,
            "60": 99.768,
            "61": 99.812,
            "62": 99.732,
            "63": 99.816,
            "64": 99.83999999999999,
            "65": 99.812,
            "66": 99.848,
            "67": 99.832,
            "68": 99.812,
            "69": 99.912,
            "70": 99.684,
            "71": 99.82799999999999,
            "72": 99.88,
            "73": 99.836,
            "74": 99.668,
            "75": 99.848,
            "76": 99.844,
            "77": 99.816,
            "78": 99.936,
            "79": 99.772,
            "80": 99.82799999999999,
            "81": 99.696,
            "82": 99.76,
            "83": 99.912,
            "84": 99.892,
            "85": 99.88,
            "86": 99.88,
            "87": 99.78399999999999,
            "88": 99.908,
            "89": 99.928
        },
        "time_train_teacher": {
            "0": 62.9575035572052,
            "1": 53.23770546913147,
            "2": 49.225404500961304,
            "3": 46.077412366867065,
            "4": 44.42666029930115,
            "5": 42.8369574546814,
            "6": 40.915568351745605,
            "7": 39.33932161331177,
            "8": 38.36401891708374,
            "9": 37.263150215148926,
            "10": 35.74594449996948,
            "11": 35.02994251251221,
            "12": 34.71450209617615,
            "13": 33.363852739334106,
            "14": 32.81009554862976,
            "15": 31.953058004379272,
            "16": 31.667452335357666,
            "17": 31.666527271270752,
            "18": 30.825939178466797,
            "19": 30.69120478630066,
            "20": 30.354680061340332,
            "21": 29.912160873413086,
            "22": 29.53491997718811,
            "23": 29.64042592048645,
            "24": 28.80823540687561,
            "25": 28.53182053565979,
            "26": 28.220959663391113,
            "27": 27.877822160720825,
            "28": 27.832093954086304,
            "29": 27.58991551399231,
            "30": 27.42383122444153,
            "31": 27.08151125907898,
            "32": 27.03446125984192,
            "33": 27.036609172821045,
            "34": 26.677980422973633,
            "35": 26.43161368370056,
            "36": 26.289685010910034,
            "37": 26.258251905441284,
            "38": 26.541974306106567,
            "39": 26.000854969024658,
            "40": 25.983338594436646,
            "41": 26.113654851913452,
            "42": 25.974077463150024,
            "43": 25.732365369796753,
            "44": 25.626807928085327,
            "45": 25.60762929916382,
            "46": 25.554357528686523,
            "47": 25.53504776954651,
            "48": 25.306575059890747,
            "49": 25.320866584777832,
            "50": 25.310069799423218,
            "51": 25.16175103187561,
            "52": 24.9046950340271,
            "53": 24.89509630203247,
            "54": 25.156963348388672,
            "55": 25.041781187057495,
            "56": 24.930689334869385,
            "57": 24.922332286834717,
            "58": 25.046308279037476,
            "59": 24.793264389038086,
            "60": 24.959184408187866,
            "61": 24.863969802856445,
            "62": 24.741124391555786,
            "63": 25.351666688919067,
            "64": 24.742589712142944,
            "65": 24.751353979110718,
            "66": 25.24436616897583,
            "67": 24.990063190460205,
            "68": 24.812962532043457,
            "69": 24.795403957366943,
            "70": 24.660703420639038,
            "71": 24.623119354248047,
            "72": 24.38865089416504,
            "73": 24.400062322616577,
            "74": 24.63062596321106,
            "75": 24.199543476104736,
            "76": 24.572237253189087,
            "77": 24.739123821258545,
            "78": 25.02755069732666,
            "79": 24.851421117782593,
            "80": 24.817835807800293,
            "81": 24.729057788848877,
            "82": 24.178691387176514,
            "83": 24.588101387023926,
            "84": 24.603330850601196,
            "85": 24.708826303482056,
            "86": 24.303244829177856,
            "87": 24.520498514175415,
            "88": 24.329103231430054,
            "89": 24.636276960372925
        },
        "time_train_student": {
            "0": 30.075480222702026,
            "1": 26.50245213508606,
            "2": 25.013527870178223,
            "3": 24.07179617881775,
            "4": 23.439140558242798,
            "5": 22.813712120056152,
            "6": 22.38615918159485,
            "7": 21.801936149597168,
            "8": 20.982460021972656,
            "9": 20.604963541030884,
            "10": 20.158044576644897,
            "11": 20.009620189666748,
            "12": 19.84384536743164,
            "13": 19.633557081222534,
            "14": 19.302407026290894,
            "15": 19.029094219207764,
            "16": 19.071990251541138,
            "17": 18.78136396408081,
            "18": 18.84618091583252,
            "19": 19.067372798919678,
            "20": 18.83541750907898,
            "21": 18.811771392822266,
            "22": 19.082885026931763,
            "23": 18.51073384284973,
            "24": 18.16555881500244,
            "25": 18.152584314346313,
            "26": 17.79197907447815,
            "27": 17.942134857177734,
            "28": 18.1728458404541,
            "29": 18.022343397140503,
            "30": 17.805431842803955,
            "31": 17.950849771499634,
            "32": 17.862245082855225,
            "33": 17.31006169319153,
            "34": 16.808554649353027,
            "35": 16.38211178779602,
            "36": 16.260600566864014,
            "37": 16.74420690536499,
            "38": 16.263965368270874,
            "39": 16.140879154205322,
            "40": 16.399057149887085,
            "41": 16.249370336532593,
            "42": 16.713905096054077,
            "43": 16.81402063369751,
            "44": 16.678030014038086,
            "45": 16.785650491714478,
            "46": 16.56963586807251,
            "47": 16.183037281036377,
            "48": 16.028966188430786,
            "49": 15.65293550491333,
            "50": 15.877192735671997,
            "51": 15.90589189529419,
            "52": 16.380188465118408,
            "53": 16.05977463722229,
            "54": 16.175450086593628,
            "55": 15.95154070854187,
            "56": 16.137251377105713,
            "57": 15.893283605575562,
            "58": 15.584934711456299,
            "59": 15.238914728164673,
            "60": 15.063626289367676,
            "61": 15.114843845367432,
            "62": 15.208338737487793,
            "63": 15.09622311592102,
            "64": 15.029364109039307,
            "65": 14.611122846603394,
            "66": 14.912657737731934,
            "67": 14.388598203659058,
            "68": 14.707895040512085,
            "69": 14.94029188156128,
            "70": 14.611454486846924,
            "71": 14.431397438049316,
            "72": 14.518897771835327,
            "73": 14.426255941390991,
            "74": 14.732024669647217,
            "75": 14.777942895889282,
            "76": 14.777985095977783,
            "77": 14.883321046829224,
            "78": 15.100520372390747,
            "79": 14.801950693130493,
            "80": 15.065265417098999,
            "81": 15.230786323547363,
            "82": 15.277556419372559,
            "83": 15.622672319412231,
            "84": 15.500864028930664,
            "85": 15.141075372695923,
            "86": 15.899543046951294,
            "87": 15.62641954421997,
            "88": 15.821087121963501,
            "89": 15.624836206436157
        },
        "time_train_distilled": {
            "0": 62.9575035572052,
            "1": 53.23770546913147,
            "2": 49.225404500961304,
            "3": 46.077412366867065,
            "4": 44.42666029930115,
            "5": 42.8369574546814,
            "6": 40.915568351745605,
            "7": 39.33932161331177,
            "8": 38.36401891708374,
            "9": 37.263150215148926,
            "10": 35.74594449996948,
            "11": 35.02994251251221,
            "12": 34.71450209617615,
            "13": 33.363852739334106,
            "14": 32.81009554862976,
            "15": 31.953058004379272,
            "16": 31.667452335357666,
            "17": 31.666527271270752,
            "18": 30.825939178466797,
            "19": 30.69120478630066,
            "20": 30.354680061340332,
            "21": 29.912160873413086,
            "22": 29.53491997718811,
            "23": 29.64042592048645,
            "24": 28.80823540687561,
            "25": 28.53182053565979,
            "26": 28.220959663391113,
            "27": 27.877822160720825,
            "28": 27.832093954086304,
            "29": 27.58991551399231,
            "30": 17.569146871566772,
            "31": 13.02916955947876,
            "32": 11.860368251800537,
            "33": 11.151298761367798,
            "34": 11.087087154388428,
            "35": 10.591827630996704,
            "36": 10.325783967971802,
            "37": 10.046757221221924,
            "38": 9.94954538345337,
            "39": 9.77909517288208,
            "40": 9.758028268814087,
            "41": 9.844791173934937,
            "42": 9.616498470306396,
            "43": 9.53748893737793,
            "44": 9.367376327514648,
            "45": 9.246551752090454,
            "46": 9.343721628189087,
            "47": 9.198716402053833,
            "48": 8.976818799972534,
            "49": 8.909116268157959,
            "50": 8.808293581008911,
            "51": 8.960900783538818,
            "52": 8.791542768478394,
            "53": 8.855557441711426,
            "54": 8.690510511398315,
            "55": 8.72229266166687,
            "56": 8.777904272079468,
            "57": 8.77581000328064,
            "58": 8.755433320999146,
            "59": 8.67050576210022,
            "60": 8.630409240722656,
            "61": 8.527080059051514,
            "62": 8.532381534576416,
            "63": 8.671219825744629,
            "64": 8.506226539611816,
            "65": 8.495958089828491,
            "66": 8.545549392700195,
            "67": 8.410229921340942,
            "68": 8.42572832107544,
            "69": 8.392877578735352,
            "70": 8.32685899734497,
            "71": 8.371131181716919,
            "72": 8.242285251617432,
            "73": 8.411260604858398,
            "74": 8.342071533203125,
            "75": 8.256834506988525,
            "76": 8.331748485565186,
            "77": 8.199342966079712,
            "78": 8.375513553619385,
            "79": 8.254286050796509,
            "80": 8.16614842414856,
            "81": 8.207472085952759,
            "82": 8.229572296142578,
            "83": 8.047707796096802,
            "84": 8.03756856918335,
            "85": 8.07958459854126,
            "86": 7.958618640899658,
            "87": 7.992201089859009,
            "88": 8.023551940917969,
            "89": 7.930057048797607
        },
        "time_test_teacher": {
            "0": 13.459051132202148,
            "1": 12.81471562385559,
            "2": 14.092408180236816,
            "3": 12.743708372116089,
            "4": 13.650711297988892,
            "5": 13.831615924835205,
            "6": 13.550032377243042,
            "7": 15.11260986328125,
            "8": 15.488234281539917,
            "9": 14.154309511184692,
            "10": 15.714200258255005,
            "11": 14.409553527832031,
            "12": 14.778735160827637,
            "13": 15.137236833572388,
            "14": 15.61942982673645,
            "15": 15.704662084579468,
            "16": 16.48331928253174,
            "17": 15.99681806564331,
            "18": 15.822876930236816,
            "19": 17.04473900794983,
            "20": 17.457371950149536,
            "21": 17.74168825149536,
            "22": 17.66381525993347,
            "23": 16.518906593322754,
            "24": 16.50948715209961,
            "25": 16.808910608291626,
            "26": 16.77737259864807,
            "27": 17.72117018699646,
            "28": 16.993974924087524,
            "29": 17.131886959075928,
            "30": 17.895824670791626,
            "31": 17.084568738937378,
            "32": 17.127084255218506,
            "33": 17.536844730377197,
            "34": 17.251863479614258,
            "35": 17.19346308708191,
            "36": 17.038898229599,
            "37": 17.210651636123657,
            "38": 16.94145679473877,
            "39": 17.71444058418274,
            "40": 17.13334035873413,
            "41": 17.843541860580444,
            "42": 17.661365747451782,
            "43": 17.291048288345337,
            "44": 17.247558116912842,
            "45": 17.326279163360596,
            "46": 17.97496724128723,
            "47": 17.33500599861145,
            "48": 17.604167699813843,
            "49": 17.9531831741333,
            "50": 17.72402858734131,
            "51": 17.593724250793457,
            "52": 17.76553702354431,
            "53": 17.974379777908325,
            "54": 18.623884677886963,
            "55": 18.03647780418396,
            "56": 17.712693691253662,
            "57": 18.348583221435547,
            "58": 18.271679639816284,
            "59": 18.68652367591858,
            "60": 18.62991428375244,
            "61": 18.758432865142822,
            "62": 19.098387479782104,
            "63": 18.34622859954834,
            "64": 18.83502197265625,
            "65": 19.053619623184204,
            "66": 18.40903377532959,
            "67": 17.963812589645386,
            "68": 18.282592296600342,
            "69": 18.080377340316772,
            "70": 18.366544723510742,
            "71": 17.750367879867554,
            "72": 17.851474046707153,
            "73": 17.64214062690735,
            "74": 18.025020599365234,
            "75": 18.202460050582886,
            "76": 18.231102228164673,
            "77": 17.893876314163208,
            "78": 18.352258682250977,
            "79": 18.245225429534912,
            "80": 17.926634788513184,
            "81": 18.233879566192627,
            "82": 18.329917430877686,
            "83": 18.247887134552002,
            "84": 18.12113308906555,
            "85": 18.177923679351807,
            "86": 18.23044466972351,
            "87": 18.496647596359253,
            "88": 18.413367748260498,
            "89": 18.423768758773804
        },
        "time_test_student": {
            "0": 7.71393084526062,
            "1": 8.40280818939209,
            "2": 8.679599523544312,
            "3": 8.863181352615356,
            "4": 9.122962951660156,
            "5": 9.868889570236206,
            "6": 9.158078908920288,
            "7": 9.411007165908813,
            "8": 10.175975799560547,
            "9": 9.42845606803894,
            "10": 9.459412574768066,
            "11": 10.314857244491577,
            "12": 9.652971744537354,
            "13": 9.559545040130615,
            "14": 10.016559362411499,
            "15": 9.660234212875366,
            "16": 9.755602598190308,
            "17": 9.646958351135254,
            "18": 9.882696390151978,
            "19": 9.860032796859741,
            "20": 9.88257884979248,
            "21": 10.1358060836792,
            "22": 9.895289659500122,
            "23": 9.72422981262207,
            "24": 9.887018918991089,
            "25": 10.52636432647705,
            "26": 9.912299633026123,
            "27": 9.995296478271484,
            "28": 10.18429970741272,
            "29": 10.064743041992188,
            "30": 9.8822181224823,
            "31": 9.979227304458618,
            "32": 9.918503046035767,
            "33": 10.265759706497192,
            "34": 10.159469366073608,
            "35": 9.9079270362854,
            "36": 10.387252569198608,
            "37": 9.887913227081299,
            "38": 10.002228498458862,
            "39": 9.91489028930664,
            "40": 9.896488666534424,
            "41": 12.175512552261353,
            "42": 9.967116594314575,
            "43": 10.13979172706604,
            "44": 10.006581544876099,
            "45": 10.004217624664307,
            "46": 10.286064624786377,
            "47": 9.964045524597168,
            "48": 10.172149181365967,
            "49": 9.907576322555542,
            "50": 9.93852949142456,
            "51": 10.349182367324829,
            "52": 10.220188617706299,
            "53": 10.038854598999023,
            "54": 10.158200979232788,
            "55": 10.008532762527466,
            "56": 9.983306407928467,
            "57": 10.043450593948364,
            "58": 10.127415895462036,
            "59": 10.143169164657593,
            "60": 9.956574201583862,
            "61": 10.111661434173584,
            "62": 10.004276514053345,
            "63": 10.04522180557251,
            "64": 9.902655124664307,
            "65": 9.69189977645874,
            "66": 10.656133890151978,
            "67": 9.867730379104614,
            "68": 9.879826068878174,
            "69": 9.880257368087769,
            "70": 9.937456130981445,
            "71": 9.925629138946533,
            "72": 9.86054515838623,
            "73": 10.647929906845093,
            "74": 10.083091735839844,
            "75": 9.995781421661377,
            "76": 9.918444871902466,
            "77": 10.06692361831665,
            "78": 10.854533910751343,
            "79": 9.950799226760864,
            "80": 10.027463674545288,
            "81": 10.31085467338562,
            "82": 10.123232364654541,
            "83": 10.5313880443573,
            "84": 9.832984447479248,
            "85": 9.9898521900177,
            "86": 10.143529653549194,
            "87": 9.960609197616577,
            "88": 10.36932897567749,
            "89": 10.21199893951416
        },
        "time_test_distilled": {
            "0": 13.459051132202148,
            "1": 12.81471562385559,
            "2": 14.092408180236816,
            "3": 12.743708372116089,
            "4": 13.650711297988892,
            "5": 13.831615924835205,
            "6": 13.550032377243042,
            "7": 15.11260986328125,
            "8": 15.488234281539917,
            "9": 14.154309511184692,
            "10": 15.714200258255005,
            "11": 14.409553527832031,
            "12": 14.778735160827637,
            "13": 15.137236833572388,
            "14": 15.61942982673645,
            "15": 15.704662084579468,
            "16": 16.48331928253174,
            "17": 15.99681806564331,
            "18": 15.822876930236816,
            "19": 17.04473900794983,
            "20": 17.457371950149536,
            "21": 17.74168825149536,
            "22": 17.66381525993347,
            "23": 16.518906593322754,
            "24": 16.50948715209961,
            "25": 16.808910608291626,
            "26": 16.77737259864807,
            "27": 17.72117018699646,
            "28": 16.993974924087524,
            "29": 17.131886959075928,
            "30": 8.676241397857666,
            "31": 9.101676225662231,
            "32": 8.546202898025513,
            "33": 9.356910705566406,
            "34": 8.650373458862305,
            "35": 8.791736841201782,
            "36": 8.499119997024536,
            "37": 8.534698009490967,
            "38": 8.57059383392334,
            "39": 8.619408369064331,
            "40": 8.49476146697998,
            "41": 8.681330680847168,
            "42": 8.666536569595337,
            "43": 8.648971557617188,
            "44": 9.184571981430054,
            "45": 8.647681951522827,
            "46": 8.959720849990845,
            "47": 8.848712682723999,
            "48": 8.770853281021118,
            "49": 8.942304849624634,
            "50": 8.75008511543274,
            "51": 9.042098760604858,
            "52": 8.821825742721558,
            "53": 9.319010257720947,
            "54": 9.127357244491577,
            "55": 9.263299703598022,
            "56": 9.18714189529419,
            "57": 9.029414892196655,
            "58": 9.06288743019104,
            "59": 9.094664812088013,
            "60": 9.121939182281494,
            "61": 9.063777208328247,
            "62": 9.240344762802124,
            "63": 9.150257587432861,
            "64": 9.729970932006836,
            "65": 9.179748773574829,
            "66": 9.345117568969727,
            "67": 9.254963159561157,
            "68": 9.346724033355713,
            "69": 9.175732374191284,
            "70": 9.272986650466919,
            "71": 9.163668155670166,
            "72": 9.222158908843994,
            "73": 9.601310968399048,
            "74": 9.295268297195435,
            "75": 9.642216920852661,
            "76": 9.31877875328064,
            "77": 9.381270170211792,
            "78": 9.424746990203857,
            "79": 9.340408325195312,
            "80": 9.36586046218872,
            "81": 9.277867794036865,
            "82": 9.357035636901855,
            "83": 9.35123085975647,
            "84": 9.822609186172485,
            "85": 9.391280174255371,
            "86": 9.654194355010986,
            "87": 9.403636455535889,
            "88": 9.417948007583618,
            "89": 9.344592809677124
        }
    }
}